nbex/__init__.py
nbex/cli.py
nbex/dev_mode.py
nbex/interactive.py
nbex/nbex.py
nbex/paths.py
nbex-0.4.1.dist-info/AUTHORS.rst
nbex-0.4.1.dist-info/LICENSE
nbex-0.4.1.dist-info/METADATA
nbex-0.4.1.dist-info/WHEEL
nbex-0.4.1.dist-info/entry_points.txt
nbex-0.4.1.dist-info/top_level.txt
nbex-0.4.1.dist-info/RECORD
