Metadata-Version: 2.1
Name: nbex
Version: 0.4.1
Summary: Support for code that works interactively and in batch mode.
Home-page: https://github.com/hoelzl/nbex
Author: Matthias Hölzl
Author-email: tc@xantira.com
License: MIT license
Keywords: nbex
Platform: UNKNOWN
Classifier: Development Status :: 2 - Pre-Alpha
Classifier: Intended Audience :: Developers
Classifier: License :: OSI Approved :: MIT License
Classifier: Natural Language :: English
Classifier: Programming Language :: Python :: 3
Classifier: Programming Language :: Python :: 3.8
Requires-Python: >=3.5
Requires-Dist: click (>=7.1.2)
Requires-Dist: ipython (>=6.0)
